{
    "appid": "22866598",
    "cloudfunctionRoot": "cloudfunctions/",
    "cloudfunctionTemplateRoot": "cloudfunctionTemplate",
    "condition": {},
    "host": "baiduboxapp",
    "preview": {
        "packageId": 1293517
    },
    "projectname": "rapstar",
    "publish": {
        "hideTips": true,
        "tips": [],
        "version": "1.0.1"
    },
    "setting": {
        "urlCheck": true
    },
    "smartProgramRoot": "miniprogram/",
    "swan": {
        "baiduboxapp": {
            "swanJsVersion": "3.200.116",
            "extensionJsVersion": "1.15.3"
        }
    }
}